{
  "id": "Q16",
  "meta": {
    "hexName": "雷地豫",
    "description": "准备。雷还没响——地底下已经在动了。准备好了再动。"
  },
  "yaos": [
    0,
    0,
    0,
    1,
    0,
    0
  ],
  "segments": {
    "status": "你处在一个需要准备的阶段。不是现在就行动——是现在开始准备行动。雷还没响，但地底下已经在动了。先建好基础、组织好力量、想清楚步骤——准备好了再动，顺序不能反。",
    "trend": "利于建立根基、组织力量。很多人直接在准备不足的情况下冲了——冲出去才发现没有后援。豫不是犹豫——是提前把该准备的东西准备好。雷需要积累——积够了自然会响。",
    "mind": "你可能觉得兴奋——事情在酝酿，看到了机会，想立刻冲上去。也可能觉得焦虑——总觉得还不够、还没准备好。两种都是正常状态。关键是兴奋不要变冲动，焦虑不要变拖延。",
    "risk": "最大的风险是不准备就冲了。另一个极端是准备过头——一直在准备、永远在准备、永远不行动。雷是需要爆发的——一直憋着不让它响，地底下就一直是闷的。准备好了就动。"
  }
}