{
    "id": "Q41",
    "meta": {
        "hexName": "山泽损",
        "description": "山下有泽，损，君子以惩忿窒欲，象征减损与修养之道"
    },
    "main": {
        "id": "Q41",
        "yaos": [1, 1, 0, 0, 0, 1],
        "segments": {
            "status": "你正处在需要主动减损的阶段，如同山体削损滋养泽水，暂时的减少是为了更好的充盈。",
            "trend": "明智的舍弃能带来更大收获，简化往往比增加更需要智慧。",
            "mind": "整理衣柜捐出多余衣物，在精简中感受拥有的丰足。",
            "risk": "过度减损可能伤及根本，要在舍弃中保留核心价值。"
        },
        "lines": [
            {
                "line": 1,
                "yaoCode": "已事遄往",
                "text": "快速处理损耗事项。立即取消不必要的订阅服务，停止资金流失。"
            },
            {
                "line": 2,
                "yaoCode": "利贞征凶",
                "text": "坚守有利行动有险。保持核心技能的精进，而非盲目拓展新领域。"
            },
            {
                "line": 3,
                "yaoCode": "三人行则损一人",
                "text": "精简团队提升效率。退出冗余的群聊，保留真正有价值的社交圈。"
            },
            {
                "line": 4,
                "yaoCode": "损其疾",
                "text": "减除不良习惯。用阅读替代刷手机，将时间投入更有益的活动。"
            },
            {
                "line": 5,
                "yaoCode": "或益之十朋之龟",
                "text": "减损后获得珍贵回馈。清理空间后发现的旧物，可能带来意外惊喜。"
            },
            {
                "line": 6,
                "yaoCode": "弗损益之",
                "text": "不损不益保持平衡。在精简与丰富间找到恰到好处的中间点。"
            }
        ]
    },
    "mutual": {
        "id": "Q41_mutual",
        "segments": {
            "status": "减损过程中显露出真正重要的部分",
            "trend": "适当的精简将提升整体效能",
            "mind": "观察园丁修剪枝叶让树木更茁壮",
            "risk": "过度减损可能失去必要的多样性"
        }
    },
    "changed": {
        "id": "Q41_changed",
        "segments": {
            "status": "从减损转向增益，需要智慧选择",
            "trend": "清空的空间将迎来更优质的填充",
            "mind": "像冬日落叶为春天新芽腾出空间",
            "risk": "长期节制可能影响生命的丰富度"
        }
    },
    "summary": "损有余而补不足"
}