{
    "id": "Q27",
    "meta": {
        "hexName": "山雷颐",
        "description": "养。养人养己。先养好自己——才有东西给别人。"
    },
    "main": {
        "id": "Q27",
        "yaos": [1, 0, 0, 0, 0, 1],
        "segments": {
            "status": "你在养东西——可能是一个团队、一段关系、一个项目，或者是你自己。养需要耐心——不能拔苗助长，不能饿着不管。养的本质是持续供给——不是一次性给够，是每天都给一点。",
            "trend": "先养好自己，再养别人。自己都是空的就要给别人——你给不了，给了也会怨。养人之前先看自己：你的能量来源是什么？那个来源稳不稳？自己的口粮不稳就去养别人——迟早两边都垮。",
            "mind": "可能会觉得自己一直在给——给时间、给精力、给钱、给情绪。但给你的回报不明显。养就是这样——投入是每天的，收获是季节性的。",
            "risk": "两个坑：一个是只养别人不养自己——养到最后自己空了。另一个是养错了东西——把精力投在不值得的人或事上。先看看对方是不是真的在吸收——有些人你喂多少漏多少。"
        },
        "lines": [
            {
                "line": 1,
                "yaoCode": "舍尔灵龟",
                "text": "你本来有很好的东西——灵龟可以不用吃东西就活下去。但你把它扔了，去羡慕别人嘴里的东西。别把自己有的丢了去追别人有的。"
            },
            {
                "line": 2,
                "yaoCode": "颠颐拂经",
                "text": "你在颠倒着养——该养上面的反而去养下面，该养自己的反而去养别人。顺序反了。先把自己的口粮稳住——再去管别人。"
            },
            {
                "line": 3,
                "yaoCode": "拂颐贞凶",
                "text": "你养的方式完全错了——坚持下去会出问题。可能是养了一个不该养的人、投了一个不该投的事。停下来，重新看——你养的东西值得吗。"
            },
            {
                "line": 4,
                "yaoCode": "颠颐吉",
                "text": "这次你颠倒是对的——你在上面的人养下面的人。作为有资源的一方去养需要被养的——这是颐卦最正的位置。"
            },
            {
                "line": 5,
                "yaoCode": "拂经居贞吉",
                "text": "你偏离了常规的方式——但这次是好的偏离。可能换了一种养法、调整了供给的节奏。不是所有的反常都是错的——有用就好。"
            },
            {
                "line": 6,
                "yaoCode": "由颐厉吉",
                "text": "你成了别人的能量来源。有危险——担子很重——但结果是好的。因为你养的方式是对的，被养的人也在成长。这种养，最后会反哺你。"
            }
        ]
    },
    "mutual": {
        "id": "Q27_mutual",
        "segments": {
            "status": "养的东西在长大。虽然慢——但在长。",
            "trend": "从单向供给到双向滋养。关系在变对等。",
            "mind": "养的过程最需要的是耐心——不是更多的投入。",
            "risk": "对方不吸收——你喂多少漏多少。该断供的时候要断。"
        }
    },
    "changed": {
        "id": "Q27_changed",
        "segments": {
            "status": "养的东西成形了。开始能自己站住了。",
            "trend": "从喂养到放手。它能自己吃了。",
            "mind": "有一种看到东西长大的欣慰。",
            "risk": "它不需要你了你还继续喂——过度喂养就是负担了。"
        }
    },
    "summary": "先养好自己——才有东西给别人。",
    "closing": "养是持续供给，不是一次性给够。每天一点，长久不断。先把自己的口粮稳住。"
}
